jobapppy/__init__.py
jobapppy/__main__.py
jobapppy/cli.py
jobapppy/environments.py
jobapppy/filters.py
jobapppy/schemas.py
jobapppy/templates/resume.md.j2
jobapppy/templates/resume.tex.j2
jobapppy-0.1.0.dist-info/METADATA
jobapppy-0.1.0.dist-info/WHEEL
jobapppy-0.1.0.dist-info/entry_points.txt
jobapppy-0.1.0.dist-info/RECORD
