Metadata-Version: 2.1
Name: jobapppy
Version: 0.1.0
Summary: Command-line tools and interfaces to generate formatted resume documents (markdown, tex, pdf, etc)
Home-page: https://cahna.github.io/jobapppy/
Keywords: resume,template
Author: Conor Heine
Author-email: conor.heine+jobapppy@gmail.com
Requires-Python: >=3.10,<3.12
Classifier: Development Status :: 4 - Beta
Classifier: Environment :: Console
Classifier: Operating System :: OS Independent
Classifier: Programming Language :: Python
Classifier: Programming Language :: Python :: 3
Classifier: Programming Language :: Python :: 3.10
Classifier: Programming Language :: Python :: 3.11
Classifier: Programming Language :: Python :: 3 :: Only
Classifier: Topic :: Office/Business
Classifier: Topic :: Other/Nonlisted Topic
Classifier: Topic :: Software Development :: Pre-processors
Classifier: Topic :: Text Processing
Classifier: Topic :: Utilities
Classifier: Typing :: Typed
Requires-Dist: Jinja2 (>=3.0.1,<4.0.0)
Requires-Dist: pydantic[email] (>=2.5.3,<3.0.0)
Requires-Dist: pyyaml (>=6.0.1,<7.0.0)
Requires-Dist: typer[all] (>=0.7.0,<0.8.0)
Project-URL: Bug Tracker, https://github.com/cahna/jobapppy/issues
Project-URL: Documentation, https://cahna.github.io/jobapppy/
Project-URL: Repository, https://github.com/cahna/jobapppy
